docusync/__init__.py
docusync/cli.py
docusync/config.py
docusync/constants.py
docusync/exceptions.py
docusync/file_operations.py
docusync/git_operations.py
docusync/logger.py
docusync/md_fixer.py
docusync/sync.py
docusync/utils.py
docusync-2.1.0.dist-info/METADATA
docusync-2.1.0.dist-info/WHEEL
docusync-2.1.0.dist-info/entry_points.txt
docusync-2.1.0.dist-info/licenses/LICENSE
docusync-2.1.0.dist-info/RECORD
