Metadata-Version: 2.4
Name: docusync
Version: 2.1.0
Summary: CLI tool for syncing documentation from multiple repositories for Docusaurus
Project-URL: Homepage, https://github.com/Roman505050/docusync
Project-URL: Repository, https://github.com/Roman505050/docusync
Project-URL: Issues, https://github.com/Roman505050/docusync/issues
Author-email: Roman Myhun <myhun59@gmail.com>
License: MIT
License-File: LICENSE
Keywords: cli,documentation,docusaurus,git,sync
Classifier: Development Status :: 4 - Beta
Classifier: Environment :: Console
Classifier: Intended Audience :: Developers
Classifier: License :: OSI Approved :: MIT License
Classifier: Operating System :: OS Independent
Classifier: Programming Language :: Python :: 3
Classifier: Programming Language :: Python :: 3.12
Classifier: Topic :: Documentation
Classifier: Topic :: Software Development :: Documentation
Classifier: Topic :: Utilities
Requires-Python: >=3.12
Requires-Dist: click>=8.1.0
Requires-Dist: pydantic-settings>=2.0.0
Requires-Dist: rich>=13.0.0
